f90wrap/pywrapgen.py
f90wrap/setuptools_ext.py
f90wrap/transform.py
f90wrap/runtime.py
f90wrap/numpy_utils.py
f90wrap/build.py
f90wrap/directc.py
f90wrap/fortran.py
f90wrap/fortrantype.py
f90wrap/arraydata.cpython-39-x86_64-linux-gnu.so
f90wrap/codegen.py
f90wrap/parser.py
f90wrap/latex.py
f90wrap/sizeof_fortran_t.cpython-39-x86_64-linux-gnu.so
f90wrap/__main__.py
f90wrap/f90wrapgen.py
f90wrap/__init__.py
f90wrap/scripts/f90doc.py
f90wrap/scripts/f2py_f90wrap.py
f90wrap/scripts/main.py
f90wrap/scripts/__init__.py
f90wrap/directc_cgen/derived_types.py
f90wrap/directc_cgen/utils.py
f90wrap/directc_cgen/module_helpers_array.py
f90wrap/directc_cgen/procedures.py
f90wrap/directc_cgen/arguments.py
f90wrap/directc_cgen/arguments_scalar.py
f90wrap/directc_cgen/procedures_return.py
f90wrap/directc_cgen/arguments_array.py
f90wrap/directc_cgen/module_helpers.py
f90wrap/directc_cgen/__init__.py
f90wrap-0.3.0.dist-info/WHEEL
f90wrap-0.3.0.dist-info/entry_points.txt
f90wrap-0.3.0.dist-info/METADATA
f90wrap-0.3.0.dist-info/RECORD
