Metadata-Version: 2.1
Name: f90wrap
Version: 0.3.0
Summary: Fortran to Python interface generator with derived type support
Author-Email: James Kermode <james.kermode@gmail.com>
Project-URL: Homepage, https://github.com/jameskermode/f90wrap
Requires-Dist: numpy>=1.13
Requires-Dist: packaging
